BorutaShap.py
BorutaShapPlus-0.1.3.dist-info/LICENSE
BorutaShapPlus-0.1.3.dist-info/METADATA
BorutaShapPlus-0.1.3.dist-info/WHEEL
BorutaShapPlus-0.1.3.dist-info/top_level.txt
BorutaShapPlus-0.1.3.dist-info/RECORD
