Metadata-Version: 2.1
Name: BorutaShapPlus
Version: 0.1.3
Summary: An updated version of the SHAP-based Boruta feature selection algorithm with some new features.
Home-page: https://github.com/AbhishekKaps/Boruta-Shap
Author: Eoghan Keany
Author-email: egnkeany@gmail.com
Maintainer: Abhishek Kapoor
Maintainer-email: abhishek.kaps001@gmail.com
License: MIT
Project-URL: Original Repository, https://github.com/Ekeany/Boruta-Shap
Project-URL: Fork Repository, https://github.com/AbhishekKaps/Boruta-Shap
Classifier: License :: OSI Approved :: MIT License
Classifier: Programming Language :: Python :: 3
License-File: LICENSE
Requires-Dist: scikit-learn
Requires-Dist: tqdm
Requires-Dist: statsmodels
Requires-Dist: matplotlib
Requires-Dist: pandas
Requires-Dist: numpy<=2.0.0
Requires-Dist: shap>=0.34.0
Requires-Dist: seaborn
Requires-Dist: scipy
